tsce/__init__.py
tsce/tsce_chat.py
tsce-0.1.23.dist-info/METADATA
tsce-0.1.23.dist-info/WHEEL
tsce-0.1.23.dist-info/top_level.txt
tsce-0.1.23.dist-info/RECORD
